mongoorm/LICENSE
mongoorm/LICENSE_CN
mongoorm/__init__.py
mongoorm/connection.py
mongoorm/cursor.py
mongoorm/meta.py
mongoorm/model_meta_class.py
mongoorm/utils.py
mongoorm/doc_model/__init__.py
mongoorm/doc_model/filter_by.py
mongoorm/doc_model/payload_dict.py
mongoorm/exceptions/__init__.py
mongoorm/extensions/__init__.py
mongoorm/extensions/all_models.py
mongoorm/fields/__init__.py
mongoorm-1.1.0.dist-info/DESCRIPTION.rst
mongoorm-1.1.0.dist-info/METADATA
mongoorm-1.1.0.dist-info/RECORD
mongoorm-1.1.0.dist-info/WHEEL
mongoorm-1.1.0.dist-info/metadata.json
mongoorm-1.1.0.dist-info/top_level.txt
